magnifier/__init__.py
magnifier/base.py
magnifier/eda/__init__.py
magnifier/eda/correlation.py
magnifier/evaluation/__init__.py
magnifier/evaluation/classification.py
magnifier/io.py
magnifier/model_experiment.py
magnifier/transformer/__init__.py
magnifier/transformer/compressing.py
magnifier/transformer/resampling.py
magnifier/transformer/time_series.py
magnifier-0.0.8.dist-info/LICENSE
magnifier-0.0.8.dist-info/METADATA
magnifier-0.0.8.dist-info/WHEEL
magnifier-0.0.8.dist-info/RECORD
